{
  "id": "linode",
  "name": "Linode (Akamai)",
  "category": "cloud",
  "description": "Cloud hosting provider with virtual servers, storage, and networking",
  "official_website": "https://linode.com",
  "documentation": "https://linode.com/docs",
  "github_repository": "https://github.com/linode",
  "license": "MIT",
  "latest_version": "1.0.0",
  "programming_languages": [
    "Generic"
  ],
  "platforms": [
    "Web"
  ],
  "package_manager": "pip",
  "installation_examples": {
    "pip": "pip install linode"
  },
  "tags": [
    "cloud",
    "tool"
  ],
  "alternatives": [],
  "popularity": 5,
  "maintained": true,
  "archived": false,
  "open_source": true,
  "last_checked": "2026-07-12",
  "last_updated": "2026-07-12"
}