{
  "id": "ant-design-mobile",
  "name": "ant-design-mobile",
  "category": "frontend",
  "description": "Essential UI blocks for building mobile web apps.",
  "official_website": "https://mobile.ant.design",
  "documentation": "https://github.com/ant-design/ant-design-mobile#readme",
  "github_repository": "https://github.com/ant-design/ant-design-mobile",
  "license": "MIT",
  "programming_languages": [
    "TypeScript"
  ],
  "platforms": [
    "Web",
    "Linux",
    "macOS",
    "Windows"
  ],
  "tags": [
    "ant-design",
    "antd",
    "antd-mobile",
    "javascript",
    "mobile",
    "react",
    "react-components",
    "typescript"
  ],
  "alternatives": [],
  "popularity": 10,
  "maintained": true,
  "archived": false,
  "open_source": true,
  "repository_statistics": {
    "stars": 12018,
    "forks": 2486,
    "open_issues": 0,
    "watchers": 0
  },
  "last_checked": "2026-07-21",
  "last_updated": "2026-07-21",
  "latest_version": "v5.42.3",
  "auto_discovered": true,
  "quality_score": 80
}