{
  "id": "wireshark",
  "name": "Wireshark",
  "category": "security",
  "description": "Network protocol analyzer for capturing and inspecting network traffic",
  "official_website": "https://wireshark.org",
  "documentation": "https://wireshark.org/docs",
  "github_repository": "https://github.com/wireshark",
  "license": "MIT",
  "latest_version": "1.0.0",
  "programming_languages": [
    "Generic"
  ],
  "platforms": [
    "Web"
  ],
  "package_manager": "pip",
  "installation_examples": {
    "pip": "pip install wireshark"
  },
  "tags": [
    "security",
    "tool",
    "library"
  ],
  "alternatives": [],
  "popularity": 5,
  "maintained": true,
  "archived": false,
  "open_source": true,
  "last_checked": "2026-07-12",
  "last_updated": "2026-07-12"
}