{
  "id": "caddy",
  "name": "Caddy",
  "category": "network",
  "description": "Web server with automatic HTTPS, HTTP/2, and a simple configuration syntax written in Go",
  "official_website": "https://caddyserver.com",
  "documentation": "https://caddyserver.com/docs",
  "github_repository": "https://github.com/caddyserver/caddy",
  "license": "Apache-2.0",
  "latest_version": "v2.11.4",
  "programming_languages": [
    "Go"
  ],
  "platforms": [
    "Linux",
    "macOS",
    "Windows"
  ],
  "package_manager": "brew",
  "installation_examples": {
    "brew": "brew install caddy"
  },
  "tags": [
    "network",
    "web-server",
    "reverse-proxy",
    "auto-https",
    "http",
    "go",
    "caddyfile",
    "http-server",
    "https",
    "tls",
    "automatic-https",
    "privacy"
  ],
  "alternatives": [
    "Nginx",
    "Apache",
    "Traefik",
    "HAProxy"
  ],
  "popularity": 10,
  "maintained": true,
  "archived": false,
  "open_source": true,
  "last_checked": "2026-07-18",
  "last_updated": "2026-07-18",
  "repository_statistics": {
    "stars": 74145,
    "forks": 4829,
    "open_issues": 0,
    "watchers": 0
  }
}