{
  "id": "torchserve",
  "name": "TorchServe",
  "category": "ai",
  "description": "Model serving framework for PyTorch models in production",
  "official_website": "https://pytorch.org/serve",
  "documentation": "https://pytorch.org/serve/docs",
  "github_repository": "https://github.com/pytorch",
  "license": "MIT",
  "latest_version": "1.0.0",
  "programming_languages": [
    "Generic"
  ],
  "platforms": [
    "Web"
  ],
  "package_manager": "pip",
  "installation_examples": {
    "pip": "pip install torchserve"
  },
  "tags": [
    "ai",
    "tool"
  ],
  "alternatives": [],
  "popularity": 5,
  "maintained": true,
  "archived": false,
  "open_source": true,
  "last_checked": "2026-07-12",
  "last_updated": "2026-07-12"
}