{
  "id": "blinker-library",
  "name": "blinker-library",
  "category": "firmware",
  "description": "An IoT Solution,Blinker library for embedded hardware. Works with Arduino R4, ESP32.",
  "official_website": "https://diandeng.tech/",
  "documentation": "https://github.com/blinker-iot/blinker-library#readme",
  "github_repository": "https://github.com/blinker-iot/blinker-library",
  "license": "MIT",
  "programming_languages": [
    "C++"
  ],
  "platforms": [
    "Linux",
    "Embedded"
  ],
  "tags": [
    "arduino",
    "ble",
    "blinker",
    "embedded",
    "esp32",
    "esp8266",
    "hardware",
    "iot",
    "wifi",
    "websockets"
  ],
  "alternatives": [],
  "popularity": 9,
  "maintained": true,
  "archived": false,
  "open_source": true,
  "repository_statistics": {
    "stars": 5181,
    "forks": 236,
    "open_issues": 0,
    "watchers": 0
  },
  "last_checked": "2026-07-21",
  "last_updated": "2026-07-21",
  "latest_version": "0.3.9",
  "auto_discovered": true,
  "quality_score": 80
}